{
    "DirectionalLight": {
        "Direction": [
            0.0,
            -0.705345630645752,
            0.07053456455469131,
            0.705345630645752
        ],
        "Intensity": [
            1.0,
            1.0,
            1.0,
            1.0
        ]
    },
    "Floor": null,
    "Metadata": {
        "Highscore": 0,
        "OptimalTime": 20.0
    },
    "Player": {
        "ArrowCamera": {
            "Direction": [
                0.0,
                0.0,
                -1.0
            ],
            "FOV": 75.0,
            "Offset": [
                0.0,
                0.20000000298023224,
                -0.75
            ],
            "Position": [
                1.0,
                1.0,
                12.0
            ]
        },
        "OversightCamera": {
            "Direction": [
                0.4423959255218506,
                -0.715688943862915,
                -0.5404399633407593
            ],
            "FOV": 75.0,
            "Offset": [
                0.0,
                0.0,
                0.0
            ],
            "Position": [
                -10.0,
                20.0,
                10.0
            ]
        }
    },
    "PointLights": [
        {
            "Color": [
                1.0,
                0.0,
                0.0,
                1.0
            ],
            "Distance": 13,
            "Position": [
                -4.0,
                0.25,
                -4.0,
                1.0
            ]
        },
        {
            "Color": [
                0.0,
                1.0,
                0.0,
                1.0
            ],
            "Distance": 13,
            "Position": [
                -4.0,
                0.25,
                4.0,
                1.0
            ]
        },
        {
            "Color": [
                0.0,
                0.0,
                1.0,
                1.0
            ],
            "Distance": 13,
            "Position": [
                4.0,
                0.25,
                -4.0,
                1.0
            ]
        },
        {
            "Color": [
                1.0,
                0.0,
                1.0,
                1.0
            ],
            "Distance": 13,
            "Position": [
                4.0,
                0.25,
                4.0,
                1.0
            ]
        },
        {
            "Color": [
                1.0,
                1.0,
                0.0,
                1.0
            ],
            "Distance": 32,
            "Position": [
                -1.0,
                0.25,
                -1.0,
                1.0
            ]
        }
    ],
    "Props": [
        {
            "Model": "floor",
            "Name": "",
            "Position": [
                0.0,
                0.0,
                0.0
            ],
            "Rotation": [
                0.0,
                0.0,
                0.0
            ],
            "Scale": [
                1.0,
                1.0,
                1.0
            ]
        }
    ],
    "Target": [
        {
            "Name": "Target1",
            "Position": [
                -5.0,
                1.1529520750045776,
                -5.0
            ],
            "Rotation": [
                0.811667263507843,
                0.811667263507843,
                0.6937058568000793
            ],
            "Scale": [
                0.25,
                0.25,
                0.25
            ]
        },
        {
            "Name": "Target2",
            "Position": [
                -5.0,
                1.152113437652588,
                5.0
            ],
            "Rotation": [
                0.811667263507843,
                0.811667263507843,
                0.9321578741073608
            ],
            "Scale": [
                0.25,
                0.25,
                0.25
            ]
        },
        {
            "Name": "Target3",
            "Position": [
                5.0,
                1.0355799198150635,
                -5.0
            ],
            "Rotation": [
                0.811667263507843,
                0.811667263507843,
                0.9714206457138062
            ],
            "Scale": [
                0.25,
                0.25,
                0.25
            ]
        },
        {
            "Name": "Target4",
            "Position": [
                5.0,
                1.1532381772994995,
                5.0
            ],
            "Rotation": [
                0.811667263507843,
                0.811667263507843,
                0.6945894956588745
            ],
            "Scale": [
                0.25,
                0.25,
                0.25
            ]
        },
        {
            "Name": "Target5",
            "Position": [
                0.0,
                1.0606573820114136,
                0.0
            ],
            "Rotation": [
                0.811667263507843,
                0.811667263507843,
                0.9997935891151428
            ],
            "Scale": [
                0.25,
                0.25,
                0.25
            ]
        },
        {
            "Name": "Target6",
            "Path": [
                {
                    "Position": [
                        0.0,
                        3.0,
                        -5.0
                    ],
                    "Time": 0.0
                },
                {
                    "Position": [
                        5.0,
                        5.0,
                        0.0
                    ],
                    "Time": 3.0
                },
                {
                    "Position": [
                        0.0,
                        2.0,
                        5.0
                    ],
                    "Time": 6.0
                },
                {
                    "Position": [
                        -5.0,
                        4.0,
                        0.0
                    ],
                    "Time": 9.0
                },
                {
                    "Position": [
                        0.0,
                        3.0,
                        -5.0
                    ],
                    "Time": 13.0
                }
            ],
            "Position": [
                0.0,
                3.0,
                -5.0
            ],
            "Rotation": [
                -2.356194496154785,
                0.27564314007759094,
                -0.0
            ],
            "Scale": [
                0.25,
                0.25,
                0.25
            ]
        }
    ],
    "Walls": {
        "WallInfo": {
            "Height": 5.0,
            "Texture": "wallTex"
        },
        "WallPoints": [
            [
                [
                    -5.0,
                    -5.0
                ],
                [
                    5.0,
                    -5.0
                ],
                [
                    5.0,
                    5.0
                ],
                [
                    3.0,
                    5.0
                ],
                [
                    3.0,
                    20.0
                ],
                [
                    5.0,
                    20.0
                ],
                [
                    5.0,
                    25.0
                ],
                [
                    -5.0,
                    25.0
                ],
                [
                    -5.0,
                    20.0
                ],
                [
                    -3.0,
                    20.0
                ],
                [
                    -3.0,
                    5.0
                ],
                [
                    -5.0,
                    5.0
                ]
            ],
            [
                [
                    2.0,
                    2.0
                ],
                [
                    2.0,
                    0.0
                ],
                [
                    0.0,
                    0.0
                ],
                [
                    0.0,
                    2.0
                ]
            ]
        ]
    }
}
